[{"name":"Abony","id":55172},{"name":"Acsa","id":55174},{"name":"Albertirsa","id":55183},{"name":"Alsónémedi","id":55185},{"name":"Aszód","id":55197},{"name":"Aszódi Járás","id":55198},{"name":"Bag","id":55201},{"name":"Biatorbágy","id":55245},{"name":"Budakalász","id":55260},{"name":"Budakeszi","id":55261},{"name":"Budakeszi Járás","id":55262},{"name":"Budaörs","id":55282},{"name":"Bugyi","id":55284},{"name":"Cegléd","id":55315},{"name":"Ceglédbercel","id":55316},{"name":"Ceglédi Járás","id":55317},{"name":"Csemő","id":55327},{"name":"Csobánka","id":55336},{"name":"Csömör","id":55350},{"name":"Dabas","id":55351},{"name":"Dabasi Járás","id":55352},{"name":"Dánszentmiklós","id":55384},{"name":"Dány","id":55385},{"name":"Délegyháza","id":55388},{"name":"Diósd","id":55362},{"name":"Domony","id":55370},{"name":"Dömsöd","id":55392},{"name":"Dunabogdány","id":55372},{"name":"Dunaharaszti","id":55374},{"name":"Dunakeszi","id":55375},{"name":"Dunakeszi Járás","id":55376},{"name":"Dunavarsány","id":55380},{"name":"Ecser","id":55394},{"name":"Érd","id":56145},{"name":"Érdi Járás","id":56146},{"name":"Erdőkertes","id":55411},{"name":"Farmos","id":55417},{"name":"Felsőpakony","id":55423},{"name":"Forrópuszta","id":55433},{"name":"Fót","id":55436},{"name":"Galgahévíz","id":55444},{"name":"Galgamácsa","id":55445},{"name":"Göd","id":55474},{"name":"Gödöllő","id":55475},{"name":"Gödöllői Járás","id":55476},{"name":"Gomba","id":55449},{"name":"Gyál","id":55456},{"name":"Gyáli Járás","id":55457},{"name":"Gyömrő","id":55458},{"name":"Halásztelek","id":55496},{"name":"Hernád","id":55507},{"name":"Hévízgyörk","id":55520},{"name":"Iklad","id":55526},{"name":"Inárcs","id":55527},{"name":"Isaszeg","id":55529},{"name":"Jászkarajenő","id":55548},{"name":"Kakucs","id":55557},{"name":"Kartal","id":55570},{"name":"Kerepes","id":55588},{"name":"Kiskunlacháza","id":55598},{"name":"Kismaros","id":55606},{"name":"Kistarcsa","id":55609},{"name":"Kocsér","id":55617},{"name":"Kóka","id":55644},{"name":"Kosd","id":55624},{"name":"Leányfalu","id":55663},{"name":"Maglód","id":55674},{"name":"Mende","id":55687},{"name":"Mogyoród","id":55707},{"name":"Monor","id":55711},{"name":"Monori Járás","id":55712},{"name":"Nagykáta","id":55753},{"name":"Nagykátai Járás","id":55754},{"name":"Nagykőrös","id":55755},{"name":"Nagykőrösi Járás","id":55756},{"name":"Nagykovácsi","id":55750},{"name":"Nagymaros","id":55757},{"name":"Nagytarcsa","id":55763},{"name":"Nyáregyháza","id":55767},{"name":"Ócsa","id":56149},{"name":"Őrbottyán","id":56171},{"name":"Örkény","id":56158},{"name":"Pánd","id":55841},{"name":"Páty","id":55847},{"name":"Pécel","id":55849},{"name":"Perbál","id":55813},{"name":"Péteri","id":55855},{"name":"Pilis","id":55817},{"name":"Pilisborosjenő","id":55818},{"name":"Piliscsaba","id":55819},{"name":"Pilisszántó","id":55822},{"name":"Pilisszentiván","id":55820},{"name":"Pilisszentkereszt","id":55821},{"name":"Pilisvörösvár","id":55823},{"name":"Pilisvörösvári Járás","id":55824},{"name":"Pomáz","id":55829},{"name":"Ráckeve","id":55872},{"name":"Ráckevei Járás","id":55873},{"name":"Solymár","id":55905},{"name":"Sóskút","id":55996},{"name":"Sülysáp","id":55998},{"name":"Szada","id":55914},{"name":"Százhalombatta","id":55971},{"name":"Szentendre","id":55934},{"name":"Szentendrei Járás","id":55935},{"name":"Szentlőrinckáta","id":55946},{"name":"Szentmártonkáta","id":55947},{"name":"Szigetcsép","id":55950},{"name":"Szigethalom","id":55951},{"name":"Szigetszentmiklós","id":55952},{"name":"Szigetszentmiklósi Járás","id":55953},{"name":"Szigetújfalu","id":55956},{"name":"Szob","id":55962},{"name":"Szobi Járás","id":55963},{"name":"Sződ","id":55977},{"name":"Sződliget","id":55978},{"name":"Táborfalva","id":56061},{"name":"Tahitótfalu","id":56003},{"name":"Taksony","id":56004},{"name":"Tápióbicske","id":56063},{"name":"Tápiógyörgye","id":56064},{"name":"Tápióság","id":56069},{"name":"Tápiószecső","id":56065},{"name":"Tápiószele","id":56066},{"name":"Tápiószentmárton","id":56067},{"name":"Tápiószőlős","id":56068},{"name":"Tárnok","id":56071},{"name":"Telki","id":56018},{"name":"Tóalmás","id":56076},{"name":"Tököl","id":56079},{"name":"Törökbálint","id":56083},{"name":"Törtel","id":56082},{"name":"Tura","id":56058},{"name":"Újhartyán","id":56161},{"name":"Újszilvás","id":56163},{"name":"Üllő","id":56168},{"name":"Úri","id":56165},{"name":"Üröm","id":56169},{"name":"Vác","id":56105},{"name":"Váci Járás","id":56106},{"name":"Vácszentlászló","id":56107},{"name":"Valkó","id":56090},{"name":"Vecsés","id":56094},{"name":"Vecsési Járás","id":56095},{"name":"Veresegyház","id":56097},{"name":"Verőce","id":56099},{"name":"Visegrád","id":56103},{"name":"Zsámbék","id":56132},{"name":"Zsámbok","id":56131}]