[{"name":"Åkirkeby","id":30990},{"name":"Albertslund","id":30577},{"name":"Albertslund Kommune","id":30578},{"name":"Allerød Kommune","id":30579},{"name":"Ballerup","id":30589},{"name":"Ballerup Kommune","id":30590},{"name":"Birkerød","id":30595},{"name":"Blovstrød","id":30598},{"name":"Bornholm Kommune","id":30601},{"name":"Brøndby Kommune","id":30610},{"name":"Charlottenlund","id":30616},{"name":"Christianshavn","id":30618},{"name":"Christiansø","id":30619},{"name":"Copenhagen","id":30620},{"name":"Dragør","id":30622},{"name":"Dragør Kommune","id":30623},{"name":"Egedal Kommune","id":30627},{"name":"Espergærde","id":30633},{"name":"Farum","id":30638},{"name":"Fløng","id":30645},{"name":"Fredensborg","id":30648},{"name":"Fredensborg Kommune","id":30649},{"name":"Frederiksberg","id":30652},{"name":"Frederiksberg Kommune","id":30654},{"name":"Frederikssund","id":30657},{"name":"Frederikssund Kommune","id":30658},{"name":"Frederiksværk","id":30659},{"name":"Furesø Kommune","id":30662},{"name":"Ganløse","id":30664},{"name":"Gentofte Kommune","id":30665},{"name":"Gilleleje","id":30666},{"name":"Gladsaxe Municipality","id":30670},{"name":"Glostrup","id":30672},{"name":"Glostrup Kommune","id":30673},{"name":"Græsted","id":30681},{"name":"Gribskov Kommune","id":30678},{"name":"Halsnæs Kommune","id":30691},{"name":"Hedehusene","id":153629},{"name":"Hellebæk","id":30700},{"name":"Helsinge","id":30701},{"name":"Helsingør","id":30702},{"name":"Helsingør Kommune","id":30703},{"name":"Herlev Kommune","id":30704},{"name":"Hillerød","id":30707},{"name":"Hillerød Kommune","id":30708},{"name":"Hornbæk","id":30722},{"name":"Høje-Taastrup Kommune","id":30736},{"name":"Hørsholm","id":30739},{"name":"Hørsholm Kommune","id":30740},{"name":"Humlebæk","id":30727},{"name":"Hundested","id":30728},{"name":"Hvidovre","id":30731},{"name":"Hvidovre Kommune","id":30732},{"name":"Ishøj","id":30745},{"name":"Ishøj Kommune","id":30746},{"name":"Jægerspris","id":30752},{"name":"Kokkedal","id":30762},{"name":"Kongens Lyngby","id":30766},{"name":"København","id":30770},{"name":"Lillerød","id":30780},{"name":"Liseleje","id":30782},{"name":"Lyngby-Tårbæk Kommune","id":30785},{"name":"Lynge","id":30786},{"name":"Måløv","id":30803},{"name":"Nexø","id":30808},{"name":"Nivå","id":30810},{"name":"Nødebo","id":30823},{"name":"Ølstykke","id":31000},{"name":"Rødovre","id":30857},{"name":"Rødovre Kommune","id":30858},{"name":"Rønne","id":30861},{"name":"Rudersdal Kommune","id":30849},{"name":"Skævinge","id":30880},{"name":"Skibby","id":30874},{"name":"Slangerup","id":30884},{"name":"Smørumnedre","id":30885},{"name":"Stavnsholt","id":30896},{"name":"Stenløse","id":30900},{"name":"Taastrup","id":30930},{"name":"Tårnby","id":30946},{"name":"Tårnby Kommune","id":30947},{"name":"Trørød","id":30944},{"name":"Vallensbæk","id":30957},{"name":"Vallensbæk Kommune","id":30958},{"name":"Vanløse","id":30960},{"name":"Værløse","id":30988},{"name":"Veksø","id":30967}]