[{"name":"Abaiang","id":65041},{"name":"Abemama","id":65042},{"name":"Ambo Village","id":65043},{"name":"Aranuka","id":65044},{"name":"Arorae","id":65045},{"name":"Bairiki Village","id":65046},{"name":"Banaba","id":65047},{"name":"Banraeaba Village","id":65049},{"name":"Beru","id":65050},{"name":"Betio Village","id":65051},{"name":"Bikenibeu Village","id":65052},{"name":"Bonriki Village","id":65053},{"name":"Buota Village","id":65054},{"name":"Butaritari","id":65055},{"name":"Eita Village","id":65056},{"name":"Kuria","id":65059},{"name":"Maiana","id":65061},{"name":"Makin","id":65062},{"name":"Makin Village","id":65063},{"name":"Marakei","id":65064},{"name":"Nawerewere Village","id":65066},{"name":"Nikunau","id":65067},{"name":"Nonouti","id":65068},{"name":"Onotoa","id":65069},{"name":"Rawannawi Village","id":65070},{"name":"Tabiteuea","id":65071},{"name":"Tamana","id":65074},{"name":"Tarawa","id":65075},{"name":"Teaoraereke Village","id":65076},{"name":"Temaiku Village","id":65077}]