[{"name":"Abasolo","id":68015},{"name":"Acámbaro","id":68087},{"name":"Adjuntas del Río","id":68088},{"name":"Aguas Buenas","id":68125},{"name":"Alcocer","id":68181},{"name":"Aldama","id":68185},{"name":"Alfaro","id":68191},{"name":"Ameche","id":68253},{"name":"Apaseo el Alto","id":68296},{"name":"Apaseo el Grande","id":68297},{"name":"Arandas","id":68329},{"name":"Atarjea","id":68392},{"name":"Bajío de Bonillas","id":68505},{"name":"Barretos","id":68523},{"name":"Barrio de Guadalupe del Mezquitillo","id":68543},{"name":"Barrón","id":68562},{"name":"Boquillas","id":68640},{"name":"Buenavista de Cortés","id":68681},{"name":"Caleras de Ameche","id":68733},{"name":"Calzada del Tepozán","id":68754},{"name":"Cañada de Bustos","id":68874},{"name":"Cañada de Caracheo","id":68875},{"name":"Cañada de Negros","id":68879},{"name":"Capulín de Bustos","id":68813},{"name":"Cárdenas","id":69660},{"name":"Carrizal Grande","id":68842},{"name":"Celaya","id":68891},{"name":"Centro Familiar la Soledad","id":68899},{"name":"Cerano","id":68904},{"name":"Cerrito de Gasca","id":68910},{"name":"Cerritos","id":68915},{"name":"Cerro Colorado","id":68923},{"name":"Cerro Gordo","id":68928},{"name":"Chamácuaro","id":68971},{"name":"Charco de Pantoja","id":68997},{"name":"Chichimequillas","id":69029},{"name":"Chirimoya (Estación Chirimoya)","id":69094},{"name":"Churipitzeo","id":69124},{"name":"Cieneguilla","id":69129},{"name":"Ciudad Manuel Doblado","id":69168},{"name":"Coachiti","id":69205},{"name":"Colonia 18 de Marzo","id":69264},{"name":"Colonia Fraccionamiento el Puente","id":69302},{"name":"Colonia Francisco Javier Mina","id":69304},{"name":"Colonia la Calzada (La Olla)","id":69393},{"name":"Colonia Latinoamericana","id":69319},{"name":"Colonia Morelos","id":69332},{"name":"Colonia Morelos de Guadalupe de Rivera","id":69336},{"name":"Colonia Nuevo México","id":69341},{"name":"Colonia Padre Hidalgo","id":69345},{"name":"Colonia Patria Nueva","id":69349},{"name":"Colonia Pedro María Anaya","id":69350},{"name":"Colonia Rafael Corrales Ayala","id":69353},{"name":"Colonia San Luis Rey","id":69367},{"name":"Comanjilla","id":69421},{"name":"Comonfort","id":69428},{"name":"Coroneo","id":69482},{"name":"Corral de Piedras de Arriba","id":69488},{"name":"Corralejo de Arriba","id":69490},{"name":"Cortazar","id":69494},{"name":"Cuarta Brigada","id":69565},{"name":"Cuchicuato","id":69605},{"name":"Cuerámaro","id":69616},{"name":"Cuesta de Peñones","id":69620},{"name":"Cupareo","id":69642},{"name":"De Parral","id":69670},{"name":"Delgado de Abajo","id":69674},{"name":"Delgado de Arriba","id":69675},{"name":"Derramadero Segundo (Infiernillo)","id":69680},{"name":"Doctor Mora","id":69699},{"name":"Dolores Hidalgo Cuna de la Independencia Nacional","id":69706},{"name":"Don Diego","id":69710},{"name":"Don Francisco","id":69711},{"name":"Duarte","id":69730},{"name":"Ejido Jesús María","id":69769},{"name":"Ejido la Joya","id":69814},{"name":"El Acebuche","id":69823},{"name":"El Canario","id":69860},{"name":"El Capulín","id":69865},{"name":"El Caracol","id":69868},{"name":"El Carmen","id":69872},{"name":"El Carretón","id":69880},{"name":"El Carrizalito","id":69883},{"name":"El Castillo","id":69887},{"name":"El CERESO","id":69852},{"name":"El Chinaco (El Pujido)","id":69901},{"name":"El Coecillo","id":69909},{"name":"El Copalillo","id":69925},{"name":"El Divisador","id":69944},{"name":"El Escoplo","id":69957},{"name":"El Espejo","id":69959},{"name":"El Fresno","id":69968},{"name":"El Gallinero","id":69975},{"name":"El Huizache","id":69992},{"name":"El Jaguey","id":69997},{"name":"El Llanito","id":70020},{"name":"El Maguey","id":70029},{"name":"El Mezquitillo","id":70036},{"name":"El Moral","id":70049},{"name":"El Nacimiento","id":70053},{"name":"El Naranjillo","id":70054},{"name":"El Picacho","id":70102},{"name":"El Puesto","id":70141},{"name":"El Recuerdo de Ancón (Xoconoxtle de Arriba)","id":70149},{"name":"El Refugio de los Sauces","id":70156},{"name":"El Sabino","id":70181},{"name":"El Salto de Espejo","id":70192},{"name":"El Salvador (Ranchito San José del Carmen)","id":70195},{"name":"El Sauz (El Sauz de Villaseñor)","id":70201},{"name":"El Tecolote","id":70212},{"name":"El Tejocote (El Domingo)","id":70216},{"name":"El Tunal","id":70245},{"name":"El Varal","id":70248},{"name":"El Vicarlo","id":70257},{"name":"El Zapote","id":70261},{"name":"Empalme Escobedo","id":70299},{"name":"Estación Corralejo","id":70341},{"name":"Estación de San Francisco","id":70360},{"name":"Estación Joaquín","id":70344},{"name":"Estación la Piedad","id":70361},{"name":"Estación Pénjamo","id":70350},{"name":"Estancia del Llano","id":70364},{"name":"Estanzuela de Romero","id":70367},{"name":"Estrada","id":70372},{"name":"Ex-Hacienda del Copal","id":70384},{"name":"Fábrica de Melchor","id":70499},{"name":"Fraccionamiento la Mezquitera","id":70451},{"name":"Fraccionamiento las Liebres","id":70456},{"name":"Fraccionamiento Paraíso Real","id":70431},{"name":"Fraccionamiento Paseo de las Torres","id":70432},{"name":"Fraccionamiento Praderas de la Venta","id":70433},{"name":"Fraccionamiento Villa Jardín","id":70445},{"name":"Fraccionamiento Villas de Guanajuato","id":70446},{"name":"Franco","id":70485},{"name":"Franco Tavera","id":70486},{"name":"Frías","id":70495},{"name":"Gachupines","id":70505},{"name":"Galerade Panales","id":70513},{"name":"Gasca","id":70521},{"name":"Gavia de Rionda","id":70522},{"name":"Guadalupe","id":70574},{"name":"Guadalupe de Paso Blanco","id":70609},{"name":"Guadalupe de Rivera","id":70610},{"name":"Guadalupe de Tambula","id":70611},{"name":"Guadalupe del Monte","id":70612},{"name":"Guanajuato","id":70618},{"name":"Hacienda Arriba","id":70650},{"name":"Hacienda de la Bolsa","id":70659},{"name":"Hacienda de Márquez","id":70658},{"name":"Hoya de Cintora (La Hoya de Arriba)","id":70712},{"name":"Huanímaro","id":70734},{"name":"Huitzatarito","id":70803},{"name":"Ibarrilla","id":70832},{"name":"Irámuco","id":70880},{"name":"Irapuato","id":70876},{"name":"Jalpilla","id":70982},{"name":"Jamaica","id":70995},{"name":"Jaral del Progreso","id":71004},{"name":"Jauregui","id":71013},{"name":"Jerécuaro","id":71021},{"name":"Jesús del Monte","id":71038},{"name":"Jícamas","id":71149},{"name":"Jocoqui","id":71066},{"name":"Juan Martín","id":71123},{"name":"Juventino Rosas","id":71144},{"name":"La Aldea","id":71170},{"name":"La Angostura","id":71174},{"name":"La Aurora","id":71178},{"name":"La Caja","id":71189},{"name":"La Calera","id":71190},{"name":"La Capilla","id":71203},{"name":"La Ciénega","id":71216},{"name":"La Cieneguita","id":71214},{"name":"La Compañía","id":71224},{"name":"La Cruz","id":71251},{"name":"La Cruz del Palmar","id":71252},{"name":"La Cuevita","id":71255},{"name":"La Ermita","id":71262},{"name":"La Escondida","id":71266},{"name":"La Estancia de San José del Carmen","id":71285},{"name":"La Estrella","id":71288},{"name":"La Gavia","id":71299},{"name":"La Joya de Calvillo","id":71334},{"name":"La Labor","id":71338},{"name":"La Laborcita","id":71341},{"name":"La Laja","id":71350},{"name":"La Lobera","id":71362},{"name":"La Luz","id":71376},{"name":"La Moncada","id":71402},{"name":"La Norita","id":71409},{"name":"La Ordeña","id":71412},{"name":"La Ortiga","id":71415},{"name":"La Palma","id":71421},{"name":"La Palmita (La Palmita de San Gabriel)","id":71429},{"name":"La Purísima","id":71470},{"name":"La Sabana","id":71481},{"name":"La Sardina","id":71484},{"name":"La Sauceda","id":71485},{"name":"La Soledad","id":71491},{"name":"La Tinaja","id":71504},{"name":"La Trinidad","id":71511},{"name":"Labor de Peralta","id":71539},{"name":"Ladrilleras del Refugio","id":71544},{"name":"Laguna de Guadalupe","id":71552},{"name":"Laguna Larga","id":71548},{"name":"Laguna Larga de Cortés","id":71549},{"name":"Landín","id":71570},{"name":"Las Ánimas","id":71657},{"name":"Las Cañas","id":71584},{"name":"Las Huertas Tercera Sección","id":71605},{"name":"Las Liebres","id":71610},{"name":"Las Masas (La Luz Masas)","id":71620},{"name":"Las Trojas","id":71646},{"name":"León","id":71666},{"name":"León de los Aldama","id":71668},{"name":"Lo de Juárez","id":71701},{"name":"Loma de la Esperanza","id":71735},{"name":"Loma de Yerbabuena","id":71733},{"name":"Loma de Zempoala","id":71734},{"name":"Loma Pelada","id":71723},{"name":"Loma Tendida","id":71724},{"name":"Los Ángeles","id":71871},{"name":"Los Arcos","id":71772},{"name":"Los Desmontes","id":71796},{"name":"Los Dolores (Las Quince Letras)","id":71798},{"name":"Los Dulces Nombres","id":71799},{"name":"Los Fierros","id":71801},{"name":"Los Galvan","id":71802},{"name":"Los Lorenzos","id":71812},{"name":"Los Mancera","id":71813},{"name":"Los Medranos","id":71815},{"name":"Los Nicolases","id":71822},{"name":"Los Ocotes","id":71824},{"name":"Los Prietos","id":71838},{"name":"Los Ramírez","id":71841},{"name":"Los Remedios","id":71843},{"name":"Los Rodríguez","id":71855},{"name":"Loza de Barrera","id":71876},{"name":"Loza de los Padres","id":71877},{"name":"Lucio Blanco (Los Gavilanes)","id":71879},{"name":"Magdalena de Araceo","id":71933},{"name":"Malagana (San Antonio del Monte)","id":71944},{"name":"Manuel Doblado","id":71959},{"name":"Maravatío del Encinal","id":71980},{"name":"Marfil","id":71989},{"name":"Marroquín","id":71999},{"name":"Medina","id":72065},{"name":"Medio Sitio","id":72066},{"name":"Menores","id":72074},{"name":"Merino","id":72078},{"name":"Mexicanos","id":72101},{"name":"Mezquite de Luna","id":72110},{"name":"Mezquite de Sotelo","id":72111},{"name":"Mezquite Gordo","id":72109},{"name":"Mineral de la Luz","id":72148},{"name":"Misión de Chichimecas","id":72160},{"name":"Molino de San José","id":72185},{"name":"Molino de Santa Ana","id":72186},{"name":"Monte Blanco","id":72197},{"name":"Monte del Coecillo","id":72209},{"name":"Monte Grande","id":72201},{"name":"Morales","id":72223},{"name":"Moroleón","id":72238},{"name":"Neutla","id":72314},{"name":"Nigromante","id":72331},{"name":"Obrajuelo","id":72435},{"name":"Ocampo","id":72441},{"name":"Ojo de Agua de Ballesteros","id":72489},{"name":"Ojo de Agua de la Trinidad","id":72495},{"name":"Ojo de Agua de Mendoza","id":72492},{"name":"Ojo de Agua del Refugio","id":72496},{"name":"Ojo Seco","id":72483},{"name":"Orduña de Abajo","id":72517},{"name":"Orduña de Arriba","id":72518},{"name":"Otates","id":72537},{"name":"Palmillas de San Juan","id":72601},{"name":"Palo Colorado","id":72608},{"name":"Panales Jamaica (Cañones)","id":72621},{"name":"Parácuaro","id":72663},{"name":"Parangarico","id":72649},{"name":"Paso de Pirules","id":72692},{"name":"Paxtle","id":72716},{"name":"Pénjamo","id":73011},{"name":"Peñuelas","id":72754},{"name":"Peralta","id":72731},{"name":"Piedras de Lumbre","id":72773},{"name":"Piedras Negras","id":72771},{"name":"Piñícuaro","id":72792},{"name":"Plan de Ayala","id":72800},{"name":"Plan Guanajuato (La Sandía)","id":72794},{"name":"Plancarte","id":72805},{"name":"Potrerillos (Guanajal)","id":72864},{"name":"Pozos","id":72874},{"name":"Prados del Rosario","id":72883},{"name":"Presa Blanca","id":72887},{"name":"Primera Fracción de Crespo","id":72896},{"name":"Providencia","id":72922},{"name":"Providencia de Nápoles","id":72923},{"name":"Pueblo Nuevo","id":72941},{"name":"Puentecillas","id":72959},{"name":"Puerta del Monte","id":72963},{"name":"Purísima de Bustos","id":72996},{"name":"Purísima de Covarrubias","id":72997},{"name":"Purísima del Progreso","id":72999},{"name":"Purísima del Rincón","id":73000},{"name":"Puroagua","id":72989},{"name":"Rancho de Guadalupe","id":73078},{"name":"Rancho Nuevo de la Cruz","id":73068},{"name":"Rancho Nuevo de la Luz","id":73069},{"name":"Rancho Nuevo del Llanito","id":73070},{"name":"Rancho Viejo","id":73074},{"name":"Rincón de Cano","id":73124},{"name":"Rincón de Parangueo","id":73132},{"name":"Rincón de Tamayo","id":73134},{"name":"Rincón del Centeno","id":73137},{"name":"Rinconadas del Bosque","id":73115},{"name":"Río Laja","id":73180},{"name":"Rizos de la Joya (Rizos del Saucillo)","id":73144},{"name":"Romita","id":73156},{"name":"Roque","id":73157},{"name":"Salamanca","id":73209},{"name":"Salitrillo","id":73220},{"name":"Salvatierra","id":73231},{"name":"San Agustín de las Flores","id":73258},{"name":"San Andrés Enguaro","id":73279},{"name":"San Ángel","id":74512},{"name":"San Antonio Calichar","id":73327},{"name":"San Antonio de Corrales","id":73364},{"name":"San Antonio de los Morales","id":73375},{"name":"San Antonio de los Tepetates","id":73377},{"name":"San Antonio de Romerillo","id":73366},{"name":"San Antonio el Chico","id":73383},{"name":"San Antonio el Rico","id":73387},{"name":"San Antonio Eménguaro","id":73332},{"name":"San Antonio Gallardo","id":73334},{"name":"San Antonio Primero","id":73345},{"name":"San Antonio Texas","id":73355},{"name":"San Bartolo de Berrios","id":73411},{"name":"San Bartolomé Aguas Calientes","id":73419},{"name":"San Bernardo","id":73438},{"name":"San Bernardo Peña Blanca","id":73442},{"name":"San Cayetano","id":73465},{"name":"San Cristóbal","id":73472},{"name":"San Diego","id":73489},{"name":"San Diego de Alcalá","id":73495},{"name":"San Diego de la Unión","id":73496},{"name":"San Elías","id":73505},{"name":"San Felipe","id":73511},{"name":"San Felipe Quiriceo","id":73521},{"name":"San Francisco","id":73542},{"name":"San Francisco (Baños de Agua Caliente)","id":73546},{"name":"San Francisco de Durán","id":73611},{"name":"San Francisco del Rincón","id":73621},{"name":"San Gabriel","id":73625},{"name":"San Gabriel y San Ignacio","id":73633},{"name":"San Gregorio","id":73640},{"name":"San Ignacio","id":73651},{"name":"San Ignacio de Hidalgo","id":73654},{"name":"San Ignacio de Rivera (Ojo de Agua)","id":73655},{"name":"San Ignacio de San José Parangueo","id":73656},{"name":"San Isidro de Gamboa","id":73686},{"name":"San Isidro de la Concepción","id":73687},{"name":"San Isidro de la Estacada","id":73688},{"name":"San Isidro de los Sauces","id":73689},{"name":"San Javier","id":73697},{"name":"San Jerónimo de Araceo","id":73724},{"name":"San José de Agua Azul","id":73807},{"name":"San José de Ayala","id":73809},{"name":"San José de Bernalejo (El Guayabo)","id":73811},{"name":"San José de Cervera","id":73813},{"name":"San José de Durán (Los Troncoso)","id":73814},{"name":"San José de Guanajuato","id":73820},{"name":"San José de la Montaña","id":73831},{"name":"San José de las Pilas","id":73833},{"name":"San José de Llanos","id":73822},{"name":"San José de Mendoza","id":73823},{"name":"San José de Rancho Nuevo (Los Arrieros)","id":73824},{"name":"San José del Cerrito de Camargo","id":73835},{"name":"San José del Potrero","id":73837},{"name":"San José del Rodeo","id":73842},{"name":"San José del Torreón","id":73845},{"name":"San José el Nuevo","id":73850},{"name":"San José Iturbide","id":73769},{"name":"San José Temascatío","id":73786},{"name":"San José Viborillas","id":73798},{"name":"San Juan Bautista Cacalote","id":73871},{"name":"San Juan de Abajo","id":73959},{"name":"San Juan de la Vega","id":73966},{"name":"San Juan de Otates","id":73962},{"name":"San Juan del Llanito","id":73974},{"name":"San Juan Grande","id":73893},{"name":"San Juan Jaripeo","id":73903},{"name":"San Juan Pan de Arriba","id":73914},{"name":"San Lorenzo","id":73991},{"name":"San Lucas","id":74023},{"name":"San Luis de la Paz","id":74060},{"name":"San Miguel de Allende","id":74228},{"name":"San Miguel del Arenal","id":74233},{"name":"San Miguel Eménguaro","id":74176},{"name":"San Miguel Octopan","id":74191},{"name":"San Nicolás de la Condesa","id":74270},{"name":"San Nicolás de los Agustinos","id":74272},{"name":"San Nicolás del Cármen","id":74275},{"name":"San Nicolás Parangueo","id":74258},{"name":"San Nicolás Temascatío","id":74263},{"name":"San Pablo Pejo","id":74298},{"name":"San Pedro de Ibarra","id":74404},{"name":"San Pedro de los Naranjos","id":74409},{"name":"San Pedro Tenango","id":74378},{"name":"San Roque","id":74440},{"name":"San Roque de Montes","id":74442},{"name":"San Roque de Torres","id":74443},{"name":"San Salvador Torrecillas","id":74450},{"name":"San Sebastián de Salitre","id":74478},{"name":"San Vicente","id":74494},{"name":"San Vicente de Flores","id":74507},{"name":"Santa Ana","id":74523},{"name":"Santa Ana Pacueco","id":74544},{"name":"Santa Anita","id":74558},{"name":"Santa Bárbara","id":74566},{"name":"Santa Catarina","id":74579},{"name":"Santa Clara","id":74599},{"name":"Santa Cruz de Juventino Rosas","id":74648},{"name":"Santa Fe de la Purísima","id":74659},{"name":"Santa María del Refugio","id":74816},{"name":"Santa Rosa","id":74838},{"name":"Santa Rosa de Lima","id":74850},{"name":"Santa Rosa de Rivas","id":74852},{"name":"Santa Rosa los Angeles","id":74853},{"name":"Santa Teresa","id":74860},{"name":"Santa Teresita de Don Diego","id":74862},{"name":"Santiago Capitiro","id":74885},{"name":"Santiago de Cuenda","id":74983},{"name":"Santiago Maravatío","id":74921},{"name":"Santo Tomás Huatzindeo","id":75028},{"name":"Sarabia","id":75040},{"name":"Serrano","id":75063},{"name":"Silao","id":75079},{"name":"Silao de la Victoria","id":75080},{"name":"Silva","id":75082},{"name":"Soledad Nueva","id":75114},{"name":"Sotelo","id":75126},{"name":"Suchitlán","id":75141},{"name":"Tamazula","id":75178},{"name":"Tarandacuao","id":75229},{"name":"Taretán","id":75232},{"name":"Tarimoro","id":75233},{"name":"Tejocote de Calera","id":75305},{"name":"Tenango el Nuevo","id":75358},{"name":"Tenería del Santuario","id":75362},{"name":"Tequisquiapan","id":75464},{"name":"Tierra Fría","id":75551},{"name":"Tomelopitos","id":75728},{"name":"Tulillos de Abajo","id":75798},{"name":"Tupataro","id":75812},{"name":"Uriangato","id":75891},{"name":"Urireo","id":75895},{"name":"Valencia de Cerro Gordo","id":75907},{"name":"Valencianita","id":75908},{"name":"Valle de Santiago","id":75924},{"name":"Valtierrilla","id":75934},{"name":"Victoria","id":75982},{"name":"Victoria de Cortazar","id":75984},{"name":"Villagrán","id":76079},{"name":"Villas de Irapuato","id":76088},{"name":"Xichú","id":76135},{"name":"Xoconoxtle el Grande","id":76183},{"name":"Yerbabuena","id":76233},{"name":"Yuriria","id":76248},{"name":"Yustis","id":76250},{"name":"Zangarro (Zangarro Nuevo)","id":76297},{"name":"Zapote de Barajas","id":76302},{"name":"Zapote de Cestao","id":76303},{"name":"Zapote de Palomas","id":76304},{"name":"Zapote de Peralta","id":76305},{"name":"Zapotillo de Mogotes","id":76306}]