[{"name":"Ayabaca","id":80567},{"name":"Bernal","id":80577},{"name":"Buenos Aires","id":80578},{"name":"Catacaos","id":80596},{"name":"Chulucanas","id":80624},{"name":"El Alto","id":80638},{"name":"Huancabamba","id":80650},{"name":"La Breita","id":80686},{"name":"La Huaca","id":80687},{"name":"La Unión","id":80692},{"name":"Las Lomas","id":80698},{"name":"Máncora","id":80727},{"name":"Marcavelica","id":80711},{"name":"Morropon","id":80721},{"name":"Paita","id":80746},{"name":"Piura","id":80765},{"name":"Provincia de Ayabaca","id":80778},{"name":"Provincia de Huancabamba","id":80831},{"name":"Provincia de Paita","id":80870},{"name":"Provincia de Piura","id":80879},{"name":"Provincia de Sullana","id":80896},{"name":"Provincia de Talara","id":80899},{"name":"Querecotillo","id":80927},{"name":"Salinera Colán","id":80937},{"name":"Salitral","id":80938},{"name":"Sechura","id":80973},{"name":"Sullana","id":80979},{"name":"Talara","id":80983},{"name":"Tambo Grande","id":80986},{"name":"Vice","id":81007}]