[{"name":"Alexandru I. Cuza","id":89926},{"name":"Andrieşeni","id":89958},{"name":"Aroneanu","id":89997},{"name":"Bădeni","id":90480},{"name":"Balș","id":90052},{"name":"Bălţaţi","id":90526},{"name":"Bârnova","id":90453},{"name":"Belceşti","id":90084},{"name":"Bivolari","id":90152},{"name":"Bohotin","id":90201},{"name":"Borosoaia","id":90232},{"name":"Bosia","id":90241},{"name":"Boureni","id":90251},{"name":"Brădicești","id":90325},{"name":"Brăeşti","id":90329},{"name":"Brătești","id":90340},{"name":"Breazu","id":90289},{"name":"Buda","id":90375},{"name":"Budăi","id":90389},{"name":"Buhalnița","id":90395},{"name":"Butea","id":90425},{"name":"Buznea","id":90433},{"name":"Cârjoaia","id":93812},{"name":"Cârniceni","id":93818},{"name":"Cepleniţa","id":90618},{"name":"Chișcăreni","id":90689},{"name":"Ciohorăni","id":90719},{"name":"Ciorteşti","id":90728},{"name":"Ciurea","id":90757},{"name":"Coarnele Caprei","id":90773},{"name":"Cogeasca","id":90788},{"name":"Comarna","id":90811},{"name":"Comuna Alexandru I. Cuza","id":90848},{"name":"Comuna Andrieşeni","id":90870},{"name":"Comuna Aroneanu","id":90896},{"name":"Comuna Balş","id":90931},{"name":"Comuna Bălţaţi","id":91227},{"name":"Comuna Bârnova","id":91190},{"name":"Comuna Belceşti","id":90949},{"name":"Comuna Bivolari","id":90999},{"name":"Comuna Brăeşti","id":91118},{"name":"Comuna Butea","id":91173},{"name":"Comuna Cepleniţa","id":91284},{"name":"Comuna Ciohorãni","id":91349},{"name":"Comuna Ciorteşti","id":91356},{"name":"Comuna Ciurea","id":91375},{"name":"Comuna Coarnele Caprei","id":91382},{"name":"Comuna Comarna","id":91407},{"name":"Comuna Costeşti","id":91457},{"name":"Comuna Costuleni","id":91461},{"name":"Comuna Cotnari","id":91466},{"name":"Comuna Cozmeşti","id":91471},{"name":"Comuna Cristeşti","id":91496},{"name":"Comuna Cucuteni","id":91520},{"name":"Comuna Dagâţa","id":91599},{"name":"Comuna Deleni","id":91611},{"name":"Comuna Dobrovăţ","id":91644},{"name":"Comuna Dolheşti","id":91655},{"name":"Comuna Drăguşeni","id":91697},{"name":"Comuna Dumeşti","id":91720},{"name":"Comuna Erbiceni","id":91749},{"name":"Comuna Fântânele","id":91807},{"name":"Comuna Focuri","id":91774},{"name":"Comuna Golãieşti","id":91899},{"name":"Comuna Gorban","id":91900},{"name":"Comuna Grajduri","id":91910},{"name":"Comuna Gropniţa","id":91925},{"name":"Comuna Grozeşti","id":91927},{"name":"Comuna Hălăuceşti","id":92040},{"name":"Comuna Hărmăneşti","id":92044},{"name":"Comuna Heleşteni","id":91995},{"name":"Comuna Holboca","id":92009},{"name":"Comuna Horleşti","id":92020},{"name":"Comuna Ion Neculce","id":92083},{"name":"Comuna Ipatele","id":92089},{"name":"Comuna Lespezi","id":92155},{"name":"Comuna Leţcani","id":92161},{"name":"Comuna Lungani","id":92211},{"name":"Comuna Mădârjac","id":92382},{"name":"Comuna Mirceşti","id":92297},{"name":"Comuna Mironeasa","id":92299},{"name":"Comuna Miroslava","id":92300},{"name":"Comuna Mirosloveşti","id":92301},{"name":"Comuna Mogoşeşti","id":92319},{"name":"Comuna Mogoşeşti-Siret","id":92320},{"name":"Comuna Moşna","id":92347},{"name":"Comuna Moţca","id":92351},{"name":"Comuna Movileni","id":92341},{"name":"Comuna Oţeleni","id":92526},{"name":"Comuna Plugari","id":92604},{"name":"Comuna Popeşti","id":92654},{"name":"Comuna Popricani","id":92658},{"name":"Comuna Prisăcani","id":92679},{"name":"Comuna Probota","id":92680},{"name":"Comuna Răchiţeni","id":92837},{"name":"Comuna Răducăneni","id":92844},{"name":"Comuna Rediu-Tătar","id":92761},{"name":"Comuna Româneşti","id":92787},{"name":"Comuna Roşcani","id":92794},{"name":"Comuna Ruginoasa","id":92808},{"name":"Comuna Scânteia","id":92901},{"name":"Comuna Scheia","id":92884},{"name":"Comuna Schitu-Duca","id":92889},{"name":"Comuna Scobinţi","id":92892},{"name":"Comuna Sineşti","id":92939},{"name":"Comuna Şipote","id":93528},{"name":"Comuna Sireţel","id":92943},{"name":"Comuna Stolniceni-Prăjescu","id":92998},{"name":"Comuna Strunga","id":93007},{"name":"Comuna Tansa","id":93124},{"name":"Comuna Tătăruşi","id":93245},{"name":"Comuna Ţibana","id":93570},{"name":"Comuna Ţibăneşti","id":93572},{"name":"Comuna Ţigănaşi","id":93574},{"name":"Comuna Todireşti","id":93165},{"name":"Comuna Tomeşti","id":93168},{"name":"Comuna Trifeşti","id":93193},{"name":"Comuna Ţuţora","id":93578},{"name":"Comuna Ungheni","id":93268},{"name":"Comuna Valea Lupului","id":93310},{"name":"Comuna Valea Seacă","id":93321},{"name":"Comuna Vânãtori","id":93432},{"name":"Comuna Victoria","id":93353},{"name":"Comuna Vlădeni","id":93388},{"name":"Comuna Voineşti","id":93399},{"name":"Conțești","id":93599},{"name":"Coropceni","id":93650},{"name":"Costești","id":93665},{"name":"Costuleni","id":93669},{"name":"Cotnari","id":93676},{"name":"Covasna","id":93679},{"name":"Cozia","id":93683},{"name":"Cozmeşti","id":93686},{"name":"Cristeşti","id":93719},{"name":"Crivești","id":93728},{"name":"Crucea","id":93742},{"name":"Cucuteni","id":93762},{"name":"Dagâţa","id":93887},{"name":"Dancu","id":93892},{"name":"Deleni","id":93915},{"name":"Dobrovăţ","id":93969},{"name":"Dolheşti","id":93983},{"name":"Domnița","id":93993},{"name":"Drăgușeni","id":94053},{"name":"Dumbrava","id":94076},{"name":"Dumbrăvița","id":94091},{"name":"Dumeşti","id":94096},{"name":"Erbiceni","id":94144},{"name":"Fântânele","id":94241},{"name":"Fărcășeni","id":94266},{"name":"Fetești","id":94161},{"name":"Focuri","id":94192},{"name":"Gârbești","id":94481},{"name":"Glodenii Gândului","id":94363},{"name":"Goești","id":94370},{"name":"Golăiești","id":94380},{"name":"Gorban","id":94382},{"name":"Goruni","id":94391},{"name":"Grajduri","id":94400},{"name":"Gropniţa","id":94420},{"name":"Grozeşti","id":94422},{"name":"Hălăuceşti","id":94602},{"name":"Hârlău","id":94588},{"name":"Hărmăneasa","id":94606},{"name":"Hărmăneștii Vechi","id":94607},{"name":"Hârtoape","id":94591},{"name":"Heci","id":94526},{"name":"Heleșteni","id":94528},{"name":"Hodora","id":94544},{"name":"Holboca","id":94549},{"name":"Horleşti","id":94564},{"name":"Iaşi","id":94630},{"name":"Iazu Nou","id":94628},{"name":"Ion Neculce","id":94675},{"name":"Ipatele","id":94683},{"name":"Iugani","id":94695},{"name":"Izvoarele","id":94706},{"name":"Lespezi","id":94782},{"name":"Leţcani","id":94791},{"name":"Liteni","id":94810},{"name":"Lunca","id":94853},{"name":"Lunca Cetățuii","id":94863},{"name":"Lungani","id":94880},{"name":"Mădârjac","id":95232},{"name":"Mănăstirea","id":95261},{"name":"Maxut","id":94940},{"name":"Mirceşti","id":95014},{"name":"Mironeasa","id":95019},{"name":"Miroslava","id":95021},{"name":"Miroslovești","id":95022},{"name":"Mogoşeşti","id":95053},{"name":"Mogoşeşti-Siret","id":95054},{"name":"Moşna","id":95088},{"name":"Moţca","id":95092},{"name":"Movileni","id":95083},{"name":"Muncelu de Sus","id":95100},{"name":"Municipiul Iaşi","id":95150},{"name":"Municipiul Paşcani","id":95166},{"name":"Munteni","id":95199},{"name":"Oraş Hârlãu","id":95531},{"name":"Oraş Podu Iloaiei","id":95569},{"name":"Oraş Târgu Frumos","id":95607},{"name":"Osoi","id":95674},{"name":"Oţeleni","id":95689},{"name":"Pârcovaci","id":95998},{"name":"Paşcani","id":95718},{"name":"Păușești","id":96036},{"name":"Perieni","id":95730},{"name":"Pietrosu","id":95786},{"name":"Plugari","id":95831},{"name":"Podolenii de Sus","id":95849},{"name":"Podu Iloaiei","id":95850},{"name":"Poiana","id":95862},{"name":"Poiana Mărului","id":95877},{"name":"Poienile","id":95893},{"name":"Popeşti","id":95909},{"name":"Popricani","id":95919},{"name":"Prisăcani","id":95956},{"name":"Probota","id":95957},{"name":"Răchiteni","id":96185},{"name":"Răducăneni","id":96199},{"name":"Războieni","id":96213},{"name":"Rediu","id":96075},{"name":"Româneşti","id":96110},{"name":"Roșcani","id":96134},{"name":"Ruginoasa","id":96148},{"name":"Satu Nou","id":96259},{"name":"Scânteia","id":96292},{"name":"Scheia","id":96265},{"name":"Schitu-Duca","id":96273},{"name":"Scobinţi","id":96277},{"name":"Sineşti","id":96352},{"name":"Şipote","id":97057},{"name":"Sireţel","id":96359},{"name":"Slobozia","id":96371},{"name":"Soci","id":96395},{"name":"Sodomeni","id":96399},{"name":"Sticlăria","id":96431},{"name":"Stolniceni-Prăjescu","id":96442},{"name":"Stornești","id":96445},{"name":"Strunga","id":96459},{"name":"Suhuleț","id":96497},{"name":"Tabăra","id":106050},{"name":"Tansa","id":106058},{"name":"Târgu Frumos","id":96583},{"name":"Tătăruşi","id":96620},{"name":"Ţibana","id":97101},{"name":"Ţibăneşti","id":97103},{"name":"Ţigănaşi","id":97106},{"name":"Todireşti","id":106115},{"name":"Tomeşti","id":106121},{"name":"Topile","id":106129},{"name":"Totoești","id":106143},{"name":"Trifeşti","id":106156},{"name":"Ţuţora","id":97110},{"name":"Uda","id":96634},{"name":"Valea Lupului","id":96732},{"name":"Valea Seacă","id":96753},{"name":"Vânători","id":96930},{"name":"Verșeni","id":96792},{"name":"Victoria","id":96805},{"name":"Vlădeni","id":96862},{"name":"Voineşti","id":96881},{"name":"Zagavia","id":96978},{"name":"Zmeu","id":97001}]