[{"name":"Abuș","id":146225},{"name":"Acățari","id":146226},{"name":"Adămuș","id":146230},{"name":"Adrian","id":146227},{"name":"Adrianu Mare","id":146228},{"name":"Adrianu Mic","id":146229},{"name":"Agrișteu","id":146231},{"name":"Albești","id":146232},{"name":"Aluniș","id":146233},{"name":"Andreneasa","id":146234},{"name":"Angofa","id":146235},{"name":"Apalina","id":146236},{"name":"Apold","id":146237},{"name":"Archita","id":146238},{"name":"Arșița","id":146239},{"name":"Ațintiș","id":146242},{"name":"Aurel Vlaicu","id":146240},{"name":"Avrămești","id":146241},{"name":"Băgaciu","id":146282},{"name":"Bahnea","id":146243},{"name":"Băița","id":146283},{"name":"Băla","id":146284},{"name":"Bălăușeri","id":146285},{"name":"Balda","id":146244},{"name":"Band","id":146245},{"name":"Bâra","id":146278},{"name":"Bărboși","id":146286},{"name":"Bărdești","id":146287},{"name":"Bârlibaș","id":146279},{"name":"Bârlibășoaia","id":146280},{"name":"Bârza","id":146281},{"name":"Batoș","id":146246},{"name":"Bedeni","id":146247},{"name":"Beica de Jos","id":146248},{"name":"Beica de Sus","id":146249},{"name":"Bereni","id":146250},{"name":"Berghia","id":146251},{"name":"Bernadea","id":146252},{"name":"Beu","id":146253},{"name":"Bezid","id":146254},{"name":"Bicașu","id":146255},{"name":"Bichiș","id":146256},{"name":"Bistra Mureșului","id":146257},{"name":"Blidireasa","id":146258},{"name":"Bobohalma","id":146259},{"name":"Bogata","id":146260},{"name":"Boiu","id":146261},{"name":"Bolintineni","id":146262},{"name":"Bologaia","id":146263},{"name":"Bord","id":146264},{"name":"Bordoșiu","id":146265},{"name":"Borzia","id":146266},{"name":"Botei","id":146267},{"name":"Botez","id":146268},{"name":"Botorca","id":146269},{"name":"Bozed","id":146270},{"name":"Bozeni","id":146271},{"name":"Brădețelu","id":146274},{"name":"Brâncovenești","id":146273},{"name":"Breaza","id":146272},{"name":"Budiu Mic","id":146275},{"name":"Bujor","id":146276},{"name":"Bujor-Hodaie","id":146277},{"name":"Căciulata","id":146345},{"name":"Căcuciu","id":146346},{"name":"Călimănești","id":146347},{"name":"Călugăreni","id":146348},{"name":"Călușeri","id":146349},{"name":"Câmpenița","id":146342},{"name":"Câmpu Cetății","id":146343},{"name":"Cându","id":146344},{"name":"Căpâlna de Sus","id":146352},{"name":"Căpeți","id":146350},{"name":"Căpușu de Câmpie","id":146351},{"name":"Cașva","id":146288},{"name":"Cecălaca","id":146289},{"name":"Ceie","id":146290},{"name":"Cerghid","id":146291},{"name":"Cerghizel","id":146292},{"name":"Ceuaș","id":146293},{"name":"Ceuașu de Câmpie","id":146294},{"name":"Chendu","id":146295},{"name":"Chețani","id":146296},{"name":"Chibed","id":146297},{"name":"Chiheru de Jos","id":146298},{"name":"Chiheru de Sus","id":146299},{"name":"Chinari","id":146300},{"name":"Chinciuș","id":146301},{"name":"Chirileu","id":146302},{"name":"Chisălița","id":146303},{"name":"Ciba","id":146304},{"name":"Cibu","id":146305},{"name":"Cinta","id":146306},{"name":"Cioarga","id":146307},{"name":"Ciobotani","id":146308},{"name":"Cipaieni","id":146309},{"name":"Cipău","id":146310},{"name":"Ciretea","id":146311},{"name":"Cirhagău","id":146312},{"name":"Ciulea","id":146313},{"name":"Ciurgău","id":146314},{"name":"Cloașterf","id":146315},{"name":"Coasta Grindului","id":146316},{"name":"Coasta Mare","id":146317},{"name":"Comori","id":146318},{"name":"Comuna Coroisânmartin","id":146319},{"name":"Comuna Ibănești Pădure","id":146320},{"name":"Comuna Rușii Munți","id":146321},{"name":"Corbești","id":146322},{"name":"Cordoș","id":146323},{"name":"Cornești","id":146324},{"name":"Coroi","id":146325},{"name":"Corunca","id":146326},{"name":"Cotorinau","id":146327},{"name":"Cotuș","id":146328},{"name":"Cozma","id":146329},{"name":"Crăciunești","id":146332},{"name":"Crăiești","id":146333},{"name":"Criș","id":146331},{"name":"Cristești","id":146330},{"name":"Cucerdea","id":146334},{"name":"Cuci","id":146335},{"name":"Cuieșd","id":146336},{"name":"Culpiu","id":146337},{"name":"Cund","id":146338},{"name":"Curețe","id":146339},{"name":"Curteni","id":146340},{"name":"Cuștelnic","id":146341},{"name":"Daia","id":146353},{"name":"Dalu","id":146354},{"name":"Dâmbău","id":146374},{"name":"Dâmbu","id":146373},{"name":"Dămieni","id":146375},{"name":"Daneș","id":146355},{"name":"Dătășeni","id":146376},{"name":"Deag","id":146356},{"name":"Deaj","id":146357},{"name":"Deda","id":146358},{"name":"Dedrad","id":146359},{"name":"Deleni","id":146360},{"name":"Dileu Nou","id":146361},{"name":"Dileu Vechi","id":146362},{"name":"Dobra","id":146363},{"name":"Drăculea Bandului","id":146365},{"name":"Drojdii","id":146364},{"name":"Dubiștea de Pădure","id":146366},{"name":"Dulcea","id":146367},{"name":"Dumbrava","id":146368},{"name":"Dumbrăvioara","id":146369},{"name":"Dumitreni","id":146370},{"name":"Dumitreștii","id":146371},{"name":"După Deal","id":146372},{"name":"Ercea","id":146377},{"name":"Eremieni","id":146378},{"name":"Eremitu","id":146379},{"name":"Ernei","id":146380},{"name":"Fânațe","id":146391},{"name":"Fânațele Mădărașului","id":146392},{"name":"Fânațele Socolului","id":146393},{"name":"Fântâna Babii","id":146394},{"name":"Fântânele","id":146395},{"name":"Fărăgău","id":146396},{"name":"Feleag","id":146381},{"name":"Filea","id":146382},{"name":"Filitelnic","id":146383},{"name":"Filpișu Mare","id":146384},{"name":"Filpișu Mic","id":146385},{"name":"Fițcău","id":146386},{"name":"Foi","id":146387},{"name":"Frunzeni","id":146388},{"name":"Fundătura","id":146390},{"name":"Fundoaia","id":146389},{"name":"Găiești","id":146418},{"name":"Gălăoaia","id":146420},{"name":"Gălățeni","id":146421},{"name":"Gălești","id":146419},{"name":"Gâmbuț","id":146417},{"name":"Gănești","id":146422},{"name":"Gaura Sângerului","id":146397},{"name":"Gheja","id":146398},{"name":"Gheorghe Doja","id":146399},{"name":"Ghidașteu","id":146400},{"name":"Ghindari","id":146401},{"name":"Ghinești","id":146402},{"name":"Giuluș","id":146403},{"name":"Giurgiș","id":146404},{"name":"Glăjărie","id":146406},{"name":"Glodeni","id":146405},{"name":"Gogan","id":146407},{"name":"Goreni","id":146408},{"name":"Gornești","id":146409},{"name":"Grădini","id":146415},{"name":"Grâușorul","id":146414},{"name":"Grebenișu de Câmpie","id":146410},{"name":"Grindeni","id":146411},{"name":"Groapa Rădăii","id":146412},{"name":"Gruișor","id":146413},{"name":"Gurghiu","id":146416},{"name":"Habic","id":146423},{"name":"Hădăreni","id":146431},{"name":"Hagău","id":146424},{"name":"Hărănglab","id":146432},{"name":"Hărțău","id":146433},{"name":"Herepea","id":146425},{"name":"Herghelia","id":146426},{"name":"Hetiur","id":146427},{"name":"Hodac","id":146428},{"name":"Hodaia","id":146429},{"name":"Hodoșa","id":146430},{"name":"Iara de Mureș","id":146434},{"name":"Ibănești-Pădure","id":146435},{"name":"Icland","id":146436},{"name":"Iclandu Mare","id":146437},{"name":"Iclănzel","id":146438},{"name":"Ideciu de Jos","id":146440},{"name":"Idicel-Pădure","id":146441},{"name":"Idiciu","id":146442},{"name":"Idrifaia","id":146443},{"name":"Iernut","id":146444},{"name":"Iernuțeni","id":146445},{"name":"Ihod","id":146446},{"name":"Ilieni","id":146447},{"name":"Ilieși","id":146448},{"name":"Ilioara","id":146449},{"name":"Iod","id":146450},{"name":"Isla","id":146451},{"name":"Iștan-Tău","id":146453},{"name":"Iștihaza","id":146454},{"name":"Ivănești","id":146452},{"name":"Jabenița","id":146455},{"name":"Jacodu","id":146456},{"name":"Jacu","id":146457},{"name":"Lăpușna","id":146478},{"name":"Larga","id":146458},{"name":"Lăscud","id":146479},{"name":"Laslău Mare","id":146459},{"name":"Laslău Mic","id":146460},{"name":"Lăureni","id":146480},{"name":"Lechincioara","id":146461},{"name":"Lechința","id":146462},{"name":"Lefaia","id":146463},{"name":"Leniș","id":146464},{"name":"Leordeni","id":146465},{"name":"Leorința","id":146466},{"name":"Leorința-Șăulia","id":146467},{"name":"Lepindea","id":146468},{"name":"Linț","id":146469},{"name":"Livezeni","id":146470},{"name":"Logig","id":146471},{"name":"Loțu","id":146472},{"name":"Luduș","id":146473},{"name":"Luieriu","id":146474},{"name":"Lunca","id":146475},{"name":"Lunca Bradului","id":146476},{"name":"Lunca Mureșului","id":146477},{"name":"Măcicășești","id":146508},{"name":"Mădăraș","id":146509},{"name":"Mădărășeni","id":146510},{"name":"Măgherani","id":146511},{"name":"Măgheruș","id":146512},{"name":"Maia","id":146481},{"name":"Maiad","id":146482},{"name":"Maiorești","id":146483},{"name":"Mălăești","id":146513},{"name":"Maldaoci","id":146484},{"name":"Malea","id":146485},{"name":"Mărășești","id":146515},{"name":"Mărculeni","id":146514},{"name":"Mătrici","id":146516},{"name":"Merișor","id":146486},{"name":"Merișoru","id":146487},{"name":"Meștera","id":146488},{"name":"Mica","id":146489},{"name":"Miercurea Nirajului","id":146490},{"name":"Mihai Viteazu","id":146491},{"name":"Miheșu de Câmpie","id":146492},{"name":"Milășel","id":146493},{"name":"Mirigioaia","id":146494},{"name":"Mitrești","id":146495},{"name":"Moara de Jos","id":146496},{"name":"Mogoaia","id":146497},{"name":"Moișa","id":146498},{"name":"Morăreni","id":146501},{"name":"Morești","id":146499},{"name":"Moruț","id":146500},{"name":"Moșuni","id":146502},{"name":"Mura Mare","id":146503},{"name":"Mura Mică","id":146504},{"name":"Mureni","id":146505},{"name":"Mureșeni","id":146506},{"name":"Murgești","id":146507},{"name":"Nadășa","id":146518},{"name":"Nadeș","id":146517},{"name":"Nandra","id":146519},{"name":"Nazna","id":146520},{"name":"Neagra","id":146521},{"name":"Neaua","id":146522},{"name":"Negrenii de Câmpie","id":146523},{"name":"Nicolești","id":146524},{"name":"Nima Milășelului","id":146525},{"name":"Nima Râciului","id":146526},{"name":"Oarba de Mureș","id":146527},{"name":"Obârșie","id":146528},{"name":"Odrihei","id":146529},{"name":"Ogra","id":146530},{"name":"Onuca","id":146531},{"name":"Ormeniș","id":146532},{"name":"Oroiu","id":146533},{"name":"Orosia","id":146534},{"name":"Orșova","id":146535},{"name":"Ozd","id":146536},{"name":"Păcureni","id":146555},{"name":"Pădurea","id":146556},{"name":"Pădureni","id":146557},{"name":"Păingeni","id":146558},{"name":"Pănet","id":146559},{"name":"Papiu Ilarian","id":146537},{"name":"Pârâu Crucii","id":146553},{"name":"Pârâu Mare","id":146554},{"name":"Păsăreni","id":146560},{"name":"Păucișoara","id":146561},{"name":"Păuloaia","id":146562},{"name":"Periș","id":146538},{"name":"Petea","id":146539},{"name":"Petelea","id":146540},{"name":"Petrilaca","id":146541},{"name":"Petrilaca de Mureș","id":146542},{"name":"Pietriș","id":146543},{"name":"Pipea","id":146544},{"name":"Poarta","id":146545},{"name":"Poduri","id":146546},{"name":"Pogăceaua","id":146547},{"name":"Poienița","id":146548},{"name":"Porumbac","id":146549},{"name":"Porumbeni","id":146550},{"name":"Pripoare","id":146551},{"name":"Pusta","id":146552},{"name":"Racameț","id":146563},{"name":"Râciu","id":146573},{"name":"Ranta","id":146564},{"name":"Râpa de Jos","id":146574},{"name":"Răstolița","id":146575},{"name":"Răzoare","id":146576},{"name":"Recea","id":146565},{"name":"Reghin","id":146182},{"name":"Remetea","id":146566},{"name":"Rigmani","id":146567},{"name":"Rora","id":146568},{"name":"Roșiori","id":146571},{"name":"Roteni","id":146569},{"name":"Roua","id":146570},{"name":"Rușii-Munți","id":146572},{"name":"Săbed","id":146618},{"name":"Săcădat","id":146620},{"name":"Săcalu de Pădure","id":146619},{"name":"Săcăreni","id":146621},{"name":"Șaeș","id":146702},{"name":"Sălard","id":146622},{"name":"Sălașuri","id":146623},{"name":"Sălcud","id":146624},{"name":"Sâmbriaș","id":146598},{"name":"Sâncraiu de Mureș","id":146599},{"name":"Șandru","id":146703},{"name":"Sângeorgiu de Câmpie","id":146600},{"name":"Sângeorgiu de Mureș","id":146601},{"name":"Sângeorgiu de Pădure","id":146602},{"name":"Sânger","id":146603},{"name":"Sângeru de Pădure","id":146604},{"name":"Sâniacob","id":146605},{"name":"Sânișor","id":146606},{"name":"Sânmărghita","id":146608},{"name":"Sânmărtinu de Câmpie","id":146609},{"name":"Sânmihai de Pădure","id":146607},{"name":"Sânpaul","id":146610},{"name":"Sânpetru de Câmpie","id":146611},{"name":"Sânsimion","id":146612},{"name":"Sântana de Mureș","id":146613},{"name":"Sântioana","id":146614},{"name":"Sântioana de Mureș","id":146615},{"name":"Sântu","id":146616},{"name":"Sânvăsii","id":146617},{"name":"Șapartoc","id":146704},{"name":"Sărățeni","id":146627},{"name":"Șardu Nirajului","id":146705},{"name":"Sărmășel","id":146626},{"name":"Sărmașu","id":146625},{"name":"Saschiz","id":146577},{"name":"Satu Nou","id":146578},{"name":"Șăulia","id":146717},{"name":"Șăulița","id":146718},{"name":"Șăușa","id":146719},{"name":"Scurta","id":146579},{"name":"Sebeș","id":146580},{"name":"Seleuș","id":146581},{"name":"Senereuș","id":146582},{"name":"Șerbeni","id":146706},{"name":"Seuca","id":146583},{"name":"Șeulia de Mureș","id":146707},{"name":"Sfântu Gheorghe","id":146584},{"name":"Sicele","id":146585},{"name":"Sighișoara","id":146586},{"name":"Șilea Nirajului","id":146708},{"name":"Șincai","id":146709},{"name":"Șincai-Fânațe","id":146710},{"name":"Șoard","id":146711},{"name":"Socolu de Câmpie","id":146587},{"name":"Șoimuș","id":146712},{"name":"Solocma","id":146588},{"name":"Solovăstru","id":146589},{"name":"Șomoștelnic","id":146713},{"name":"Șoromiclea","id":146714},{"name":"Sovata","id":146590},{"name":"Stânceni","id":146593},{"name":"Ștefanca","id":146715},{"name":"Ștefăneaca","id":146716},{"name":"Stejărenii","id":146592},{"name":"Stejeriș","id":146591},{"name":"Sub Pădure","id":146594},{"name":"Suplac","id":146595},{"name":"Suseni","id":146596},{"name":"Suveica","id":146597},{"name":"Tăblășeni","id":146645},{"name":"Tâmpa","id":146642},{"name":"Târgu Mureș","id":146643},{"name":"Târnăveni","id":146644},{"name":"Tău","id":146646},{"name":"Tăureni","id":146647},{"name":"Teleac","id":146628},{"name":"Țigmandru","id":146720},{"name":"Țiptelnic","id":146721},{"name":"Tireu","id":146629},{"name":"Tirimia","id":146630},{"name":"Tirimioara","id":146631},{"name":"Tisieu","id":146632},{"name":"Titiana","id":146633},{"name":"Toaca","id":146634},{"name":"Tofalău","id":146635},{"name":"Toldal","id":146636},{"name":"Tonciu","id":146637},{"name":"Țopa","id":146722},{"name":"Torba","id":146638},{"name":"Trei Sate","id":146639},{"name":"Troița","id":146640},{"name":"Tușinu","id":146641},{"name":"Uila","id":146648},{"name":"Ulieș","id":146649},{"name":"Ungheni","id":146650},{"name":"Uricea","id":146651},{"name":"Urisiu de Jos","id":146652},{"name":"Urisiu de Sus","id":146653},{"name":"Ursoaia","id":146654},{"name":"Vădaș","id":146690},{"name":"Vadu","id":146655},{"name":"Vaidacuta","id":146656},{"name":"Vaideiu","id":146657},{"name":"Valea","id":146658},{"name":"Valea Albeștiului","id":146659},{"name":"Valea Dăii","id":146660},{"name":"Valea Frăției","id":146661},{"name":"Valea Glodului","id":146662},{"name":"Valea Iclandului","id":146663},{"name":"Valea Izvoarelor","id":146664},{"name":"Valea Largă","id":146665},{"name":"Valea Mare","id":146666},{"name":"Valea Pădurii","id":146667},{"name":"Valea Rece","id":146668},{"name":"Valea Sânmărtinului","id":146671},{"name":"Valea Sânpetrului","id":146672},{"name":"Valea Șapartocului","id":146676},{"name":"Valea Sasului","id":146669},{"name":"Valea Seacă","id":146670},{"name":"Valea Șurii","id":146677},{"name":"Valea Ulieșului","id":146673},{"name":"Valea Ungurului","id":146674},{"name":"Valea Urieșului","id":146675},{"name":"Văleni","id":146691},{"name":"Vălenii","id":146692},{"name":"Vălenii de Mureș","id":146693},{"name":"Vălișoara","id":146694},{"name":"Vălureni","id":146695},{"name":"Vânători","id":146689},{"name":"Vărgata","id":146696},{"name":"Vătava","id":146697},{"name":"Venchi","id":146678},{"name":"Veța","id":146679},{"name":"Vețca","id":146680},{"name":"Vidrasău","id":146681},{"name":"Viforoasa","id":146682},{"name":"Viilor","id":146683},{"name":"Viișoara","id":146684},{"name":"Vișinelu","id":146685},{"name":"Voiniceni","id":146686},{"name":"Voivodeni","id":146687},{"name":"Vulcan","id":146688},{"name":"Zagăr","id":146698},{"name":"Zăpodea","id":146701},{"name":"Zau de Câmpie","id":146699},{"name":"Zimți","id":146700}]